so_vits_svc_fork/__init__.py
so_vits_svc_fork/__main__.py
so_vits_svc_fork/dataset.py
so_vits_svc_fork/f0.py
so_vits_svc_fork/gui.py
so_vits_svc_fork/hparams.py
so_vits_svc_fork/logger.py
so_vits_svc_fork/py.typed
so_vits_svc_fork/train.py
so_vits_svc_fork/utils.py
so_vits_svc_fork/cluster/__init__.py
so_vits_svc_fork/cluster/train_cluster.py
so_vits_svc_fork/inference/__init__.py
so_vits_svc_fork/inference/core.py
so_vits_svc_fork/inference/main.py
so_vits_svc_fork/modules/__init__.py
so_vits_svc_fork/modules/attentions.py
so_vits_svc_fork/modules/commons.py
so_vits_svc_fork/modules/descriminators.py
so_vits_svc_fork/modules/encoders.py
so_vits_svc_fork/modules/flows.py
so_vits_svc_fork/modules/losses.py
so_vits_svc_fork/modules/mel_processing.py
so_vits_svc_fork/modules/modules.py
so_vits_svc_fork/modules/synthesizers.py
so_vits_svc_fork/modules/decoders/__init__.py
so_vits_svc_fork/modules/decoders/f0.py
so_vits_svc_fork/modules/decoders/hifigan/__init__.py
so_vits_svc_fork/modules/decoders/hifigan/_models.py
so_vits_svc_fork/modules/decoders/hifigan/_utils.py
so_vits_svc_fork/modules/decoders/mb_istft/__init__.py
so_vits_svc_fork/modules/decoders/mb_istft/_generators.py
so_vits_svc_fork/modules/decoders/mb_istft/_loss.py
so_vits_svc_fork/modules/decoders/mb_istft/_pqmf.py
so_vits_svc_fork/modules/decoders/mb_istft/_stft.py
so_vits_svc_fork/modules/decoders/mb_istft/_stft_loss.py
so_vits_svc_fork/preprocessing/__init__.py
so_vits_svc_fork/preprocessing/preprocess_classify.py
so_vits_svc_fork/preprocessing/preprocess_flist_config.py
so_vits_svc_fork/preprocessing/preprocess_hubert_f0.py
so_vits_svc_fork/preprocessing/preprocess_resample.py
so_vits_svc_fork/preprocessing/preprocess_speaker_diarization.py
so_vits_svc_fork/preprocessing/preprocess_split.py
so_vits_svc_fork/preprocessing/preprocess_utils.py
so_vits_svc_fork-4.2.27.dist-info/licenses/LICENSE
so_vits_svc_fork-4.2.27.dist-info/METADATA
so_vits_svc_fork-4.2.27.dist-info/WHEEL
so_vits_svc_fork-4.2.27.dist-info/entry_points.txt
so_vits_svc_fork-4.2.27.dist-info/top_level.txt
so_vits_svc_fork-4.2.27.dist-info/RECORD
