Metadata-Version: 2.4
Name: so-vits-svc-fork
Version: 4.2.27
Summary: A fork of so-vits-svc.
Author-email: 34j <34j.95a2p@simplelogin.com>
License: MIT
Project-URL: Bug Tracker, https://github.com/voicepaw/so-vits-svc-fork/issues
Project-URL: Changelog, https://github.com/voicepaw/so-vits-svc-fork/blob/main/CHANGELOG.md
Project-URL: documentation, https://so-vits-svc-fork.readthedocs.io
Project-URL: repository, https://github.com/voicepaw/so-vits-svc-fork
Classifier: Development Status :: 2 - Pre-Alpha
Classifier: Intended Audience :: Developers
Classifier: Natural Language :: English
Classifier: Operating System :: OS Independent
Classifier: Programming Language :: Python :: 3.9
Classifier: Programming Language :: Python :: 3.10
Classifier: Programming Language :: Python :: 3.11
Classifier: Programming Language :: Python :: 3.12
Classifier: Programming Language :: Python :: 3.13
Classifier: Topic :: Software Development :: Libraries
Requires-Python: >=3.9
License-File: LICENSE
Requires-Dist: click>=8.1.8
Requires-Dist: cm-time>=0.1.2
Requires-Dist: fastapi>=0.116.1
Requires-Dist: librosa>=0.11.0
Requires-Dist: lightning>=2.5.5
Requires-Dist: matplotlib>=3.9.4
Requires-Dist: numpy>=2.0.2
Requires-Dist: pebble>=5.1.3
Requires-Dist: praat-parselmouth>=0.4.6
Requires-Dist: pysimplegui-4-foss>=4.60.4.1
Requires-Dist: pyworld>=0.3.5
Requires-Dist: requests>=2.32.5
Requires-Dist: rich>=14.1.0
Requires-Dist: scipy>=1.13.1
Requires-Dist: sounddevice>=0.5.2
Requires-Dist: soundfile>=0.13.1
Requires-Dist: tensorboard>=2.20.0
Requires-Dist: tensorboardx>=2.6.4
Requires-Dist: torch>=2.8.0
Requires-Dist: torchaudio>=2.8.0
Requires-Dist: torchcrepe>=0.0.24
Requires-Dist: tqdm>=4.67.1
Requires-Dist: tqdm-joblib>=0.0.4
Requires-Dist: transformers>=4.56.1
Dynamic: license-file
